bondzai.davinsy_py-0.0.19-py3.10-nspkg.pth
bondzai/davinsy_py/__init__.py
bondzai/davinsy_py/davinsy.py
bondzai/davinsy_py/enums.py
bondzai/davinsy_py/logger.py
bondzai/davinsy_py/model.py
bondzai/davinsy_py/operations.py
bondzai/davinsy_py/preproc.py
bondzai/davinsy_py/utils.py
bondzai.davinsy_py-0.0.19.dist-info/METADATA
bondzai.davinsy_py-0.0.19.dist-info/NOTICE
bondzai.davinsy_py-0.0.19.dist-info/WHEEL
bondzai.davinsy_py-0.0.19.dist-info/namespace_packages.txt
bondzai.davinsy_py-0.0.19.dist-info/top_level.txt
bondzai.davinsy_py-0.0.19.dist-info/zip-safe
bondzai.davinsy_py-0.0.19.dist-info/RECORD
