Metadata-Version: 2.1
Name: bondzai.davinsy-py
Version: 0.0.19
Summary: Bondzai Python API
Home-page: UNKNOWN
Author: Bondzai
License: Apache License 2.0
Keywords: davinsy,bondzai
Platform: UNKNOWN
Classifier: Programming Language :: Python :: 3
Classifier: License :: OSI Approved :: Apache Software License
Classifier: Operating System :: OS Independent
License-File: NOTICE
Requires-Dist: numpy (>=1.24.3)
Requires-Dist: pyyaml (==6.0)
